ixai/__init__.py
ixai/__version__.py
ixai/explainer/__init__.py
ixai/explainer/base.py
ixai/explainer/pfi.py
ixai/explainer/sage/__init__.py
ixai/explainer/sage/batch.py
ixai/explainer/sage/incremental.py
ixai/explainer/sage/interval.py
ixai/imputer/__init__.py
ixai/imputer/base.py
ixai/imputer/default_imputer.py
ixai/imputer/marginal_imputer.py
ixai/imputer/tree_imputer.py
ixai/storage/__init__.py
ixai/storage/base.py
ixai/storage/batch_storage.py
ixai/storage/geometric_reservoir_storage.py
ixai/storage/interval_storage.py
ixai/storage/reservoir_storage.py
ixai/storage/sequence_storage.py
ixai/storage/tree_storage.py
ixai/storage/uniform_reservoir_storage.py
ixai/utils/__init__.py
ixai/utils/tracker/__init__.py
ixai/utils/tracker/base.py
ixai/utils/tracker/exponential_smoothing.py
ixai/utils/tracker/multi_value.py
ixai/utils/tracker/sliding_window.py
ixai/utils/tracker/welford.py
ixai/utils/validators/__init__.py
ixai/utils/validators/loss.py
ixai/utils/validators/model.py
ixai/utils/wrappers/__init__.py
ixai/utils/wrappers/base.py
ixai/utils/wrappers/river.py
ixai/utils/wrappers/sklearn.py
ixai/utils/wrappers/torch.py
ixai/visualization/__init__.py
ixai/visualization/change_plotter.py
ixai/visualization/color.py
ixai/visualization/config.py
ixai/visualization/line_plots.py
ixai/visualization/plotting.py
ixai/visualization/waterfall_plots.py
ixai-0.1.3.dist-info/LICENSE
ixai-0.1.3.dist-info/METADATA
ixai-0.1.3.dist-info/WHEEL
ixai-0.1.3.dist-info/top_level.txt
ixai-0.1.3.dist-info/zip-safe
ixai-0.1.3.dist-info/RECORD
