Metadata-Version: 2.1
Name: ixai
Version: 0.1.3
Summary: Explainable Artificial Intelligence for dynamic and Incremental models.
Home-page: https://github.com/mmschlk/iXAI
Author: Maximilian Muschalik
Author-email: maximilian.muschalik@ifi.lmu.de
License: MIT
Project-URL: Tracker, https://github.com/mmschlk/iXAI/issues?q=is%3Aissue+label%3Abug
Project-URL: Source, https://github.com/mmschlk/iXAI
Keywords: python,machine learning,online learning,xai
Classifier: Development Status :: 3 - Alpha
Classifier: License :: OSI Approved :: MIT License
Classifier: Intended Audience :: Developers
Classifier: Intended Audience :: Science/Research
Classifier: Topic :: Scientific/Engineering :: Artificial Intelligence
Classifier: Programming Language :: Python
Classifier: Programming Language :: Python :: 3.8
Classifier: Programming Language :: Python :: 3.9
Classifier: Programming Language :: Python :: 3.10
Classifier: Programming Language :: Python :: 3.11
Requires-Python: >=3.8.0
License-File: LICENSE
Requires-Dist: river
Requires-Dist: matplotlib
Requires-Dist: pandas
Requires-Dist: numpy
Requires-Dist: tqdm
Provides-Extra: dev
Requires-Dist: river ; extra == 'dev'
Requires-Dist: matplotlib ; extra == 'dev'
Requires-Dist: pandas ; extra == 'dev'
Requires-Dist: numpy ; extra == 'dev'
Requires-Dist: tqdm ; extra == 'dev'
Requires-Dist: pytest ; extra == 'dev'
Requires-Dist: scikit-learn ; extra == 'dev'
Requires-Dist: flake8 ; extra == 'dev'
Requires-Dist: torch ; extra == 'dev'
Requires-Dist: openml ; extra == 'dev'
Provides-Extra: docs
Requires-Dist: river ; extra == 'docs'
Requires-Dist: matplotlib ; extra == 'docs'
Requires-Dist: pandas ; extra == 'docs'
Requires-Dist: numpy ; extra == 'docs'
Requires-Dist: tqdm ; extra == 'docs'
Requires-Dist: pytest ; extra == 'docs'
Requires-Dist: scikit-learn ; extra == 'docs'
Requires-Dist: flake8 ; extra == 'docs'
Requires-Dist: torch ; extra == 'docs'
Requires-Dist: openml ; extra == 'docs'
Requires-Dist: sphinx ; extra == 'docs'
